setting_manager/__init__.py
setting_manager/manager.py
setting_manager/fastapi/__init__.py
setting_manager/fastapi/route.py
setting_manager/fastapi/templates/grouped_settings.html
setting_manager/fastapi/templates/settings.html
setting_manager/storage/__init__.py
setting_manager/storage/base.py
setting_manager/storage/memory.py
setting_manager/storage/mongo.py
setting_manager/sync/__init__.py
setting_manager-0.5.4.dist-info/METADATA
setting_manager-0.5.4.dist-info/WHEEL
setting_manager-0.5.4.dist-info/RECORD
