Metadata-Version: 2.4
Name: setting-manager
Version: 0.5.4
Summary: A flexible settings management library
Project-URL: Homepage, https://github.com/Frojen/setting-manager
Project-URL: Changelog, https://github.com/Frojen/setting-manager/blob/main/CHANGELOG.md
Author-email: Konstantin Zhmurko <prog@zhmyrko.ru>
License: MIT
Keywords: feature flag,library,setting
Classifier: Development Status :: 3 - Alpha
Classifier: Intended Audience :: Developers
Classifier: License :: OSI Approved :: MIT License
Classifier: Operating System :: OS Independent
Classifier: Programming Language :: Python :: 3.11
Requires-Python: >=3.11
Requires-Dist: pydantic
Requires-Dist: pydantic-settings
Provides-Extra: fastapi
Requires-Dist: fastapi; extra == 'fastapi'
Provides-Extra: mongo
Requires-Dist: motor; extra == 'mongo'
